aioskybell/__init__.py
aioskybell/device.py
aioskybell/exceptions.py
aioskybell/py.typed
aioskybell/utils.py
aioskybell/helpers/__init__.py
aioskybell/helpers/const.py
aioskybell/helpers/errors.py
aioskybell/helpers/models.py
aioskybell-23.12.0.dist-info/LICENSE
aioskybell-23.12.0.dist-info/METADATA
aioskybell-23.12.0.dist-info/WHEEL
aioskybell-23.12.0.dist-info/top_level.txt
aioskybell-23.12.0.dist-info/RECORD
