Metadata-Version: 2.1
Name: aioskybell
Version: 23.12.0
Summary: A Skybell HD Python library running on Python 3.
Home-page: https://github.com/tkdrob/aioskybell
Author: Robert Hillis
Author-email: tkdrob4390@yahoo.com
License: MIT license
Keywords: aioskybell,skybell
Classifier: Intended Audience :: Developers
Classifier: License :: OSI Approved :: MIT License
Classifier: Natural Language :: English
Classifier: Operating System :: OS Independent
Classifier: Programming Language :: Python :: 3
Classifier: Programming Language :: Python :: 3.9
Classifier: Programming Language :: Python :: 3.10
Classifier: Programming Language :: Python :: 3.11
Classifier: Programming Language :: Python :: 3.12
Classifier: Topic :: Software Development :: Libraries :: Python Modules
Requires-Python: >=3.9
License-File: LICENSE
Requires-Dist: aiohttp<4.0,>=3.6.1
Requires-Dist: aiofiles>=0.3.0
Requires-Dist: ciso8601>=1.0.1
